conanx/__init__.py
conanx/enums.py
conanx/errors.py
conanx/main.py
conanx/requirements.txt
conanx/requirements_dev.txt
conanx/requirements_extend.txt
conanx/requirements_osx.txt
conanx/commands/__init__.py
conanx/commands/create.py
conanx/commands/make.py
conanx/utils/__init__.py
conanx/utils/files.py
conanx/utils/log.py
conanx-0.0.1.dist-info/LICENSE.md
conanx-0.0.1.dist-info/METADATA
conanx-0.0.1.dist-info/WHEEL
conanx-0.0.1.dist-info/entry_points.txt
conanx-0.0.1.dist-info/top_level.txt
conanx-0.0.1.dist-info/RECORD
